LICENSE
MANIFEST.in
README.md
setup.py
cocoa/QuickGlass/PXGlass.h
cocoa/QuickGlass/PXGlass.m
cocoa/QuickGlass/QuickGlass-Prefix.pch
cocoa/QuickGlass/QuickGlass.1
cocoa/QuickGlass/main.m
cocoa/QuickGlass.xcodeproj/project.pbxproj
cocoa/QuickGlass.xcodeproj/project.xcworkspace/contents.xcworkspacedata
cocoa/QuickGlass.xcodeproj/project.xcworkspace/xcuserdata/Vayu.xcuserdatad/UserInterfaceState.xcuserstate
cocoa/QuickGlass.xcodeproj/xcuserdata/Vayu.xcuserdatad/xcschemes/QuickGlass.xcscheme
cocoa/QuickGlass.xcodeproj/xcuserdata/Vayu.xcuserdatad/xcschemes/xcschememanagement.plist
pyglass/__init__.py
pyglass/api.py
pyglass/models.py
pyglass/settings.py
pyglass/utils.py
pyglass.egg-info/PKG-INFO
pyglass.egg-info/SOURCES.txt
pyglass.egg-info/dependency_links.txt
pyglass.egg-info/not-zip-safe
pyglass.egg-info/requires.txt
pyglass.egg-info/top_level.txt
pyglass/pdf/__init__.py
pyglass/pdf/api.py
pyglass/quicklook/__init__.py
pyglass/quicklook/api.py
pyglass/quicklook/export.py
pyglass/quicklook/models.py
pyglass/sketch/__init__.py
pyglass/sketch/api.py
pyglass/sketch/export.py
pyglass/sketch/models.py
pyglass/sketch/parse.py
vendor/SketchTool/README.txt
vendor/SketchTool/RELEASE NOTES.txt
vendor/SketchTool/sketchmigrate
vendor/SketchTool/sketchtool
vendor/SketchTool/sketchtool resources.bundle/Contents/Info.plist
vendor/SketchTool/sketchtool resources.bundle/Contents/Resources/noise-1.png
vendor/SketchTool/sketchtool resources.bundle/Contents/Resources/noise-2.png
vendor/SketchTool/sketchtool resources.bundle/Contents/Resources/noise-3.png
vendor/SketchTool/sketchtool resources.bundle/Contents/Resources/noise-4.png
vendor/SketchTool/sketchtool resources.bundle/Contents/Resources/en.lproj/InfoPlist.strings