Metadata-Version: 1.1
Name: pyglass
Version: 0.1.1
Summary: Mac OS X File Preview Generator
Home-page: http://github.com/Pixelapse/pyglass
Author: Pixelapse
Author-email: hello@pixelapse.com
License: The MIT License
